{"gameId":"0022200464","gameCode":"20221220/WASPHX","gameStatus":3,"gameStatusText":"Final","period":4,"gameClock":"PT00M00.00S","gameTimeUTC":"2022-12-21T02:00:00Z","gameEt":"2022-12-20T21:00:00Z","awayTeamId":1610612764,"homeTeamId":1610612756,"duration":"2:20","attendance":17071,"sellout":1,"seriesGameNumber":"","seriesText":"","ifNecessary":false,"arena":{"arenaId":1000051,"arenaName":"Footprint Center","arenaCity":"Phoenix","arenaState":"AZ","arenaCountry":"US","arenaTimezone":"Mountain","arenaStreetAddress":"","arenaPostalCode":""},"officials":[{"personId":101283,"name":"Brian Forte","nameI":"B. Forte","firstName":"Brian","familyName":"Forte","jerseyNum":"45  ","assignment":""},{"personId":202058,"name":"James Williams","nameI":"J. Williams","firstName":"James","familyName":"Williams","jerseyNum":"60  ","assignment":""},{"personId":1627961,"name":"Brandon Adair","nameI":"B. Adair","firstName":"Brandon","familyName":"Adair","jerseyNum":"67  ","assignment":""}],"broadcasters":{"nationalBroadcasters":[],"nationalRadioBroadcasters":[],"nationalOttBroadcasters":[],"homeTvBroadcasters":[{"broadcasterId":1000336,"broadcastDisplay":"BSAZ","broadcasterVideoLink":""}],"homeRadioBroadcasters":[{"broadcasterId":1598,"broadcastDisplay":"KMVP/KSUN","broadcasterVideoLink":""}],"homeOttBroadcasters":[],"awayTvBroadcasters":[{"broadcasterId":1660,"broadcastDisplay":"NBCSWA","broadcasterVideoLink":"http://stream.nbcsports.com/rsn/nba-wizards-live-stream"}],"awayRadioBroadcasters":[{"broadcasterId":1139,"broadcastDisplay":"WTEM","broadcasterVideoLink":""}],"awayOttBroadcasters":[]},"homeTeam":{"teamId":1610612756,"teamName":"Suns","teamCity":"Phoenix","teamTricode":"PHX","teamSlug":"suns","teamWins":19,"teamLosses":13,"score":110,"inBonus":"","timeoutsRemaining":0,"seed":0,"statistics":{"minutes":"240:00","fieldGoalsMade":41,"fieldGoalsAttempted":89,"fieldGoalsPercentage":0.461,"threePointersMade":13,"threePointersAttempted":32,"threePointersPercentage":0.406,"freeThrowsMade":15,"freeThrowsAttempted":19,"freeThrowsPercentage":0.789,"reboundsOffensive":15,"reboundsDefensive":29,"reboundsTotal":44,"assists":26,"steals":2,"blocks":1,"turnovers":14,"foulsPersonal":23,"points":110,"plusMinusPoints":-3},"periods":[{"period":1,"periodType":"REGULAR","score":30},{"period":2,"periodType":"REGULAR","score":18},{"period":3,"periodType":"REGULAR","score":30},{"period":4,"periodType":"REGULAR","score":32}],"players":[{"personId":1628969,"firstName":"Mikal","familyName":"Bridges","nameI":"M. Bridges","playerSlug":"mikal-bridges","position":"F","comment":"","jerseyNum":"","statistics":{"minutes":"39:28","fieldGoalsMade":4,"fieldGoalsAttempted":11,"fieldGoalsPercentage":0.364,"threePointersMade":1,"threePointersAttempted":4,"threePointersPercentage":0.25,"freeThrowsMade":1,"freeThrowsAttempted":2,"freeThrowsPercentage":0.5,"reboundsOffensive":1,"reboundsDefensive":2,"reboundsTotal":3,"assists":3,"steals":0,"blocks":0,"turnovers":4,"foulsPersonal":3,"points":10,"plusMinusPoints":-6}},{"personId":1628470,"firstName":"Torrey","familyName":"Craig","nameI":"T. Craig","playerSlug":"torrey-craig","position":"F","comment":"","jerseyNum":"","statistics":{"minutes":"30:04","fieldGoalsMade":3,"fieldGoalsAttempted":7,"fieldGoalsPercentage":0.429,"threePointersMade":0,"threePointersAttempted":2,"threePointersPercentage":0,"freeThrowsMade":0,"freeThrowsAttempted":0,"freeThrowsPercentage":0,"reboundsOffensive":5,"reboundsDefensive":3,"reboundsTotal":8,"assists":2,"steals":0,"blocks":0,"turnovers":0,"foulsPersonal":3,"points":6,"plusMinusPoints":-19}},{"personId":1629028,"firstName":"Deandre","familyName":"Ayton","nameI":"D. Ayton","playerSlug":"deandre-ayton","position":"C","comment":"","jerseyNum":"","statistics":{"minutes":"32:07","fieldGoalsMade":12,"fieldGoalsAttempted":20,"fieldGoalsPercentage":0.6,"threePointersMade":0,"threePointersAttempted":0,"threePointersPercentage":0,"freeThrowsMade":6,"freeThrowsAttempted":6,"freeThrowsPercentage":1,"reboundsOffensive":4,"reboundsDefensive":9,"reboundsTotal":13,"assists":0,"steals":0,"blocks":1,"turnovers":4,"foulsPersonal":5,"points":30,"plusMinusPoints":-16}},{"personId":1627814,"firstName":"Damion","familyName":"Lee","nameI":"D. Lee","playerSlug":"damion-lee","position":"G","comment":"","jerseyNum":"","statistics":{"minutes":"17:39","fieldGoalsMade":1,"fieldGoalsAttempted":2,"fieldGoalsPercentage":0.5,"threePointersMade":0,"threePointersAttempted":1,"threePointersPercentage":0,"freeThrowsMade":0,"freeThrowsAttempted":0,"freeThrowsPercentage":0,"reboundsOffensive":0,"reboundsDefensive":2,"reboundsTotal":2,"assists":0,"steals":0,"blocks":0,"turnovers":1,"foulsPersonal":2,"points":2,"plusMinusPoints":-5}},{"personId":101108,"firstName":"Chris","familyName":"Paul","nameI":"C. Paul","playerSlug":"chris-paul","position":"G","comment":"","jerseyNum":"","statistics":{"minutes":"35:38","fieldGoalsMade":3,"fieldGoalsAttempted":11,"fieldGoalsPercentage":0.273,"threePointersMade":1,"threePointersAttempted":3,"threePointersPercentage":0.333,"freeThrowsMade":5,"freeThrowsAttempted":7,"freeThrowsPercentage":0.714,"reboundsOffensive":2,"reboundsDefensive":2,"reboundsTotal":4,"assists":11,"steals":2,"blocks":0,"turnovers":3,"foulsPersonal":3,"points":12,"plusMinusPoints":-10}},{"personId":1630688,"firstName":"Ish","familyName":"Wainright","nameI":"I. Wainright","playerSlug":"ish-wainright","position":"","comment":"","jerseyNum":"","statistics":{"minutes":"21:30","fieldGoalsMade":1,"fieldGoalsAttempted":5,"fieldGoalsPercentage":0.2,"threePointersMade":0,"threePointersAttempted":2,"threePointersPercentage":0,"freeThrowsMade":0,"freeThrowsAttempted":0,"freeThrowsPercentage":0,"reboundsOffensive":2,"reboundsDefensive":3,"reboundsTotal":5,"assists":1,"steals":0,"blocks":0,"turnovers":0,"foulsPersonal":1,"points":2,"plusMinusPoints":18}},{"personId":1630613,"firstName":"Duane","familyName":"Washington Jr.","nameI":"D. Washington Jr.","playerSlug":"duane-washington-jr","position":"","comment":"","jerseyNum":"","statistics":{"minutes":"12:22","fieldGoalsMade":4,"fieldGoalsAttempted":8,"fieldGoalsPercentage":0.5,"threePointersMade":2,"threePointersAttempted":4,"threePointersPercentage":0.5,"freeThrowsMade":0,"freeThrowsAttempted":0,"freeThrowsPercentage":0,"reboundsOffensive":0,"reboundsDefensive":2,"reboundsTotal":2,"assists":3,"steals":0,"blocks":0,"turnovers":0,"foulsPersonal":0,"points":10,"plusMinusPoints":7}},{"personId":1629013,"firstName":"Landry","familyName":"Shamet","nameI":"L. Shamet","playerSlug":"landry-shamet","position":"","comment":"","jerseyNum":"","statistics":{"minutes":"35:23","fieldGoalsMade":10,"fieldGoalsAttempted":21,"fieldGoalsPercentage":0.476,"threePointersMade":9,"threePointersAttempted":16,"threePointersPercentage":0.563,"freeThrowsMade":2,"freeThrowsAttempted":2,"freeThrowsPercentage":1,"reboundsOffensive":0,"reboundsDefensive":2,"reboundsTotal":2,"assists":5,"steals":0,"blocks":0,"turnovers":1,"foulsPersonal":2,"points":31,"plusMinusPoints":4}},{"personId":202687,"firstName":"Bismack","familyName":"Biyombo","nameI":"B. Biyombo","playerSlug":"bismack-biyombo","position":"","comment":"","jerseyNum":"","statistics":{"minutes":"15:49","fieldGoalsMade":3,"fieldGoalsAttempted":4,"fieldGoalsPercentage":0.75,"threePointersMade":0,"threePointersAttempted":0,"threePointersPercentage":0,"freeThrowsMade":1,"freeThrowsAttempted":2,"freeThrowsPercentage":0.5,"reboundsOffensive":1,"reboundsDefensive":4,"reboundsTotal":5,"assists":1,"steals":0,"blocks":0,"turnovers":1,"foulsPersonal":4,"points":7,"plusMinusPoints":12}},{"personId":1626164,"firstName":"Devin","familyName":"Booker","nameI":"D. Booker","playerSlug":"devin-booker","position":"","comment":"DND - Injury/Illness","jerseyNum":"","statistics":{"minutes":"","fieldGoalsMade":0,"fieldGoalsAttempted":0,"fieldGoalsPercentage":0,"threePointersMade":0,"threePointersAttempted":0,"threePointersPercentage":0,"freeThrowsMade":0,"freeThrowsAttempted":0,"freeThrowsPercentage":0,"reboundsOffensive":0,"reboundsDefensive":0,"reboundsTotal":0,"assists":0,"steals":0,"blocks":0,"turnovers":0,"foulsPersonal":0,"points":0,"plusMinusPoints":0}},{"personId":203967,"firstName":"Dario","familyName":"Saric","nameI":"D. Saric","playerSlug":"dario-saric","position":"","comment":"DNP - Coach's Decision","jerseyNum":"","statistics":{"minutes":"","fieldGoalsMade":0,"fieldGoalsAttempted":0,"fieldGoalsPercentage":0,"threePointersMade":0,"threePointersAttempted":0,"threePointersPercentage":0,"freeThrowsMade":0,"freeThrowsAttempted":0,"freeThrowsPercentage":0,"reboundsOffensive":0,"reboundsDefensive":0,"reboundsTotal":0,"assists":0,"steals":0,"blocks":0,"turnovers":0,"foulsPersonal":0,"points":0,"plusMinusPoints":0}}],"inactives":[{"personId":1629661,"firstName":"Cameron","familyName":"Johnson","jerseyNum":"23  "},{"personId":1629111,"firstName":"Jock","familyName":"Landale","jerseyNum":"11  "},{"personId":1626166,"firstName":"Cameron","familyName":"Payne","jerseyNum":"15  "},{"personId":203109,"firstName":"Jae","familyName":"Crowder","jerseyNum":"99  "},{"personId":1629006,"firstName":"Josh","familyName":"Okogie","jerseyNum":"2   "}],"starters":{"minutes":"154:56","fieldGoalsMade":23,"fieldGoalsAttempted":51,"fieldGoalsPercentage":0.451,"threePointersMade":2,"threePointersAttempted":10,"threePointersPercentage":0.2,"freeThrowsMade":12,"freeThrowsAttempted":15,"freeThrowsPercentage":0.8,"reboundsOffensive":12,"reboundsDefensive":18,"reboundsTotal":30,"assists":16,"steals":2,"blocks":1,"turnovers":12,"foulsPersonal":16,"points":60},"bench":{"minutes":"154:56","fieldGoalsMade":18,"fieldGoalsAttempted":38,"fieldGoalsPercentage":0.474,"threePointersMade":11,"threePointersAttempted":22,"threePointersPercentage":0.5,"freeThrowsMade":3,"freeThrowsAttempted":4,"freeThrowsPercentage":0.75,"reboundsOffensive":3,"reboundsDefensive":11,"reboundsTotal":14,"assists":10,"steals":0,"blocks":0,"turnovers":2,"foulsPersonal":7,"points":50}},"awayTeam":{"teamId":1610612764,"teamName":"Wizards","teamCity":"Washington","teamTricode":"WAS","teamSlug":"wizards","teamWins":12,"teamLosses":20,"score":113,"inBonus":"","timeoutsRemaining":0,"seed":0,"statistics":{"minutes":"240:00","fieldGoalsMade":38,"fieldGoalsAttempted":80,"fieldGoalsPercentage":0.475,"threePointersMade":11,"threePointersAttempted":27,"threePointersPercentage":0.407,"freeThrowsMade":26,"freeThrowsAttempted":37,"freeThrowsPercentage":0.703,"reboundsOffensive":9,"reboundsDefensive":32,"reboundsTotal":41,"assists":22,"steals":9,"blocks":4,"turnovers":9,"foulsPersonal":14,"points":113,"plusMinusPoints":3},"periods":[{"period":1,"periodType":"REGULAR","score":27},{"period":2,"periodType":"REGULAR","score":26},{"period":3,"periodType":"REGULAR","score":27},{"period":4,"periodType":"REGULAR","score":33}],"players":[{"personId":1630166,"firstName":"Deni","familyName":"Avdija","nameI":"D. Avdija","playerSlug":"deni-avdija","position":"F","comment":"","jerseyNum":"","statistics":{"minutes":"36:12","fieldGoalsMade":4,"fieldGoalsAttempted":8,"fieldGoalsPercentage":0.5,"threePointersMade":2,"threePointersAttempted":5,"threePointersPercentage":0.4,"freeThrowsMade":6,"freeThrowsAttempted":6,"freeThrowsPercentage":1,"reboundsOffensive":1,"reboundsDefensive":9,"reboundsTotal":10,"assists":4,"steals":0,"blocks":1,"turnovers":0,"foulsPersonal":4,"points":16,"plusMinusPoints":11}},{"personId":1628398,"firstName":"Kyle","familyName":"Kuzma","nameI":"K. Kuzma","playerSlug":"kyle-kuzma","position":"F","comment":"","jerseyNum":"","statistics":{"minutes":"36:48","fieldGoalsMade":10,"fieldGoalsAttempted":19,"fieldGoalsPercentage":0.526,"threePointersMade":5,"threePointersAttempted":10,"threePointersPercentage":0.5,"freeThrowsMade":4,"freeThrowsAttempted":6,"freeThrowsPercentage":0.667,"reboundsOffensive":0,"reboundsDefensive":6,"reboundsTotal":6,"assists":6,"steals":2,"blocks":0,"turnovers":2,"foulsPersonal":0,"points":29,"plusMinusPoints":7}},{"personId":1629655,"firstName":"Daniel","familyName":"Gafford","nameI":"D. Gafford","playerSlug":"daniel-gafford","position":"C","comment":"","jerseyNum":"","statistics":{"minutes":"29:24","fieldGoalsMade":5,"fieldGoalsAttempted":6,"fieldGoalsPercentage":0.833,"threePointersMade":0,"threePointersAttempted":0,"threePointersPercentage":0,"freeThrowsMade":2,"freeThrowsAttempted":6,"freeThrowsPercentage":0.333,"reboundsOffensive":5,"reboundsDefensive":4,"reboundsTotal":9,"assists":1,"steals":1,"blocks":0,"turnovers":1,"foulsPersonal":2,"points":12,"plusMinusPoints":-4}},{"personId":203078,"firstName":"Bradley","familyName":"Beal","nameI":"B. Beal","playerSlug":"bradley-beal","position":"G","comment":"","jerseyNum":"","statistics":{"minutes":"35:17","fieldGoalsMade":8,"fieldGoalsAttempted":20,"fieldGoalsPercentage":0.4,"threePointersMade":0,"threePointersAttempted":2,"threePointersPercentage":0,"freeThrowsMade":11,"freeThrowsAttempted":14,"freeThrowsPercentage":0.786,"reboundsOffensive":2,"reboundsDefensive":4,"reboundsTotal":6,"assists":6,"steals":1,"blocks":1,"turnovers":2,"foulsPersonal":1,"points":27,"plusMinusPoints":25}},{"personId":1628420,"firstName":"Monte","familyName":"Morris","nameI":"M. Morris","playerSlug":"monte-morris","position":"G","comment":"","jerseyNum":"","statistics":{"minutes":"36:23","fieldGoalsMade":4,"fieldGoalsAttempted":10,"fieldGoalsPercentage":0.4,"threePointersMade":1,"threePointersAttempted":2,"threePointersPercentage":0.5,"freeThrowsMade":0,"freeThrowsAttempted":1,"freeThrowsPercentage":0,"reboundsOffensive":1,"reboundsDefensive":1,"reboundsTotal":2,"assists":3,"steals":3,"blocks":1,"turnovers":0,"foulsPersonal":0,"points":9,"plusMinusPoints":11}},{"personId":203115,"firstName":"Will","familyName":"Barton","nameI":"W. Barton","playerSlug":"will-barton","position":"","comment":"","jerseyNum":"","statistics":{"minutes":"17:26","fieldGoalsMade":2,"fieldGoalsAttempted":5,"fieldGoalsPercentage":0.4,"threePointersMade":2,"threePointersAttempted":4,"threePointersPercentage":0.5,"freeThrowsMade":0,"freeThrowsAttempted":0,"freeThrowsPercentage":0,"reboundsOffensive":0,"reboundsDefensive":1,"reboundsTotal":1,"assists":1,"steals":0,"blocks":0,"turnovers":3,"foulsPersonal":0,"points":6,"plusMinusPoints":-23}},{"personId":201959,"firstName":"Taj","familyName":"Gibson","nameI":"T. Gibson","playerSlug":"taj-gibson","position":"","comment":"","jerseyNum":"","statistics":{"minutes":"18:36","fieldGoalsMade":2,"fieldGoalsAttempted":2,"fieldGoalsPercentage":1,"threePointersMade":0,"threePointersAttempted":0,"threePointersPercentage":0,"freeThrowsMade":2,"freeThrowsAttempted":2,"freeThrowsPercentage":1,"reboundsOffensive":0,"reboundsDefensive":2,"reboundsTotal":2,"assists":1,"steals":2,"blocks":1,"turnovers":1,"foulsPersonal":5,"points":6,"plusMinusPoints":8}},{"personId":1630557,"firstName":"Corey","familyName":"Kispert","nameI":"C. Kispert","playerSlug":"corey-kispert","position":"","comment":"","jerseyNum":"","statistics":{"minutes":"18:17","fieldGoalsMade":2,"fieldGoalsAttempted":5,"fieldGoalsPercentage":0.4,"threePointersMade":1,"threePointersAttempted":3,"threePointersPercentage":0.333,"freeThrowsMade":1,"freeThrowsAttempted":2,"freeThrowsPercentage":0.5,"reboundsOffensive":0,"reboundsDefensive":2,"reboundsTotal":2,"assists":0,"steals":0,"blocks":0,"turnovers":0,"foulsPersonal":0,"points":6,"plusMinusPoints":-12}},{"personId":1630692,"firstName":"Jordan","familyName":"Goodwin","nameI":"J. Goodwin","playerSlug":"jordan-goodwin","position":"","comment":"","jerseyNum":"","statistics":{"minutes":"11:37","fieldGoalsMade":1,"fieldGoalsAttempted":5,"fieldGoalsPercentage":0.2,"threePointersMade":0,"threePointersAttempted":1,"threePointersPercentage":0,"freeThrowsMade":0,"freeThrowsAttempted":0,"freeThrowsPercentage":0,"reboundsOffensive":0,"reboundsDefensive":3,"reboundsTotal":3,"assists":0,"steals":0,"blocks":0,"turnovers":0,"foulsPersonal":2,"points":2,"plusMinusPoints":-8}},{"personId":1630264,"firstName":"Anthony","familyName":"Gill","nameI":"A. Gill","playerSlug":"anthony-gill","position":"","comment":"DNP - Coach's Decision","jerseyNum":"","statistics":{"minutes":"","fieldGoalsMade":0,"fieldGoalsAttempted":0,"fieldGoalsPercentage":0,"threePointersMade":0,"threePointersAttempted":0,"threePointersPercentage":0,"freeThrowsMade":0,"freeThrowsAttempted":0,"freeThrowsPercentage":0,"reboundsOffensive":0,"reboundsDefensive":0,"reboundsTotal":0,"assists":0,"steals":0,"blocks":0,"turnovers":0,"foulsPersonal":0,"points":0,"plusMinusPoints":0}},{"personId":204001,"firstName":"Kristaps","familyName":"Porzingis","nameI":"K. Porzingis","playerSlug":"kristaps-porzingis","position":"","comment":"DND - Injury/Illness","jerseyNum":"","statistics":{"minutes":"","fieldGoalsMade":0,"fieldGoalsAttempted":0,"fieldGoalsPercentage":0,"threePointersMade":0,"threePointersAttempted":0,"threePointersPercentage":0,"freeThrowsMade":0,"freeThrowsAttempted":0,"freeThrowsPercentage":0,"reboundsOffensive":0,"reboundsDefensive":0,"reboundsTotal":0,"assists":0,"steals":0,"blocks":0,"turnovers":0,"foulsPersonal":0,"points":0,"plusMinusPoints":0}}],"inactives":[{"personId":1629653,"firstName":"Devon","familyName":"Dotson","jerseyNum":"15  "},{"personId":1626153,"firstName":"Delon","familyName":"Wright","jerseyNum":"55  "},{"personId":1631098,"firstName":"Johnny","familyName":"Davis","jerseyNum":"1   "},{"personId":1630176,"firstName":"Vernon","familyName":"Carey Jr.","jerseyNum":"13  "},{"personId":1629060,"firstName":"Rui","familyName":"Hachimura","jerseyNum":"8   "},{"personId":1630225,"firstName":"Isaiah","familyName":"Todd","jerseyNum":"14  "}],"starters":{"minutes":"174:04","fieldGoalsMade":31,"fieldGoalsAttempted":63,"fieldGoalsPercentage":0.492,"threePointersMade":8,"threePointersAttempted":19,"threePointersPercentage":0.421,"freeThrowsMade":23,"freeThrowsAttempted":33,"freeThrowsPercentage":0.697,"reboundsOffensive":9,"reboundsDefensive":24,"reboundsTotal":33,"assists":20,"steals":7,"blocks":3,"turnovers":5,"foulsPersonal":7,"points":93},"bench":{"minutes":"174:04","fieldGoalsMade":5,"fieldGoalsAttempted":15,"fieldGoalsPercentage":0.333,"threePointersMade":3,"threePointersAttempted":8,"threePointersPercentage":0.375,"freeThrowsMade":1,"freeThrowsAttempted":2,"freeThrowsPercentage":0.5,"reboundsOffensive":0,"reboundsDefensive":6,"reboundsTotal":6,"assists":1,"steals":0,"blocks":0,"turnovers":3,"foulsPersonal":2,"points":14}},"lastFiveMeetings":{"meetings":[{"recencyOrder":1,"gameId":"0022100798","gameTimeUTC":"2022-02-06T00:00:00Z","gameEt":"2022-02-05T19:00:00Z","gameStatus":3,"gameStatusText":"Final","gameClock":"PT00M00.00S","awayTeam":{"teamId":1610612756,"teamCity":"Phoenix","teamName":"Suns","teamTricode":"PHX","teamSlug":"suns","score":95,"wins":42,"losses":10},"homeTeam":{"teamId":1610612764,"teamCity":"Washington","teamName":"Wizards","teamTricode":"WAS","teamSlug":"wizards","score":80,"wins":24,"losses":28}},{"recencyOrder":2,"gameId":"0022100432","gameTimeUTC":"2021-12-17T02:00:00Z","gameEt":"2021-12-16T21:00:00Z","gameStatus":3,"gameStatusText":"Final","gameClock":"PT00M00.00S","awayTeam":{"teamId":1610612764,"teamCity":"Washington","teamName":"Wizards","teamTricode":"WAS","teamSlug":"wizards","score":98,"wins":15,"losses":15},"homeTeam":{"teamId":1610612756,"teamCity":"Phoenix","teamName":"Suns","teamTricode":"PHX","teamSlug":"suns","score":118,"wins":23,"losses":5}},{"recencyOrder":3,"gameId":"0022000803","gameTimeUTC":"2021-04-11T02:00:00Z","gameEt":"2021-04-10T22:00:00Z","gameStatus":3,"gameStatusText":"Final","gameClock":"PT00M00.00S","awayTeam":{"teamId":1610612764,"teamCity":"Washington","teamName":"Wizards","teamTricode":"WAS","teamSlug":"wizards","score":106,"wins":19,"losses":33},"homeTeam":{"teamId":1610612756,"teamCity":"Phoenix","teamName":"Suns","teamTricode":"PHX","teamSlug":"suns","score":134,"wins":37,"losses":15}},{"recencyOrder":4,"gameId":"0022000152","gameTimeUTC":"2021-01-12T00:00:00Z","gameEt":"2021-01-11T19:00:00Z","gameStatus":3,"gameStatusText":"Final","gameClock":"PT00M00.00S","awayTeam":{"teamId":1610612756,"teamCity":"Phoenix","teamName":"Suns","teamTricode":"PHX","teamSlug":"suns","score":107,"wins":7,"losses":4},"homeTeam":{"teamId":1610612764,"teamCity":"Washington","teamName":"Wizards","teamTricode":"WAS","teamSlug":"wizards","score":128,"wins":3,"losses":8}},{"recencyOrder":5,"gameId":"0021901235","gameTimeUTC":"2020-07-31T20:00:00Z","gameEt":"2020-07-31T16:00:00Z","gameStatus":3,"gameStatusText":"Final","gameClock":"PT00M00.00S","awayTeam":{"teamId":1610612756,"teamCity":"Phoenix","teamName":"Suns","teamTricode":"PHX","teamSlug":"suns","score":125,"wins":27,"losses":39},"homeTeam":{"teamId":1610612764,"teamCity":"Washington","teamName":"Wizards","teamTricode":"WAS","teamSlug":"wizards","score":112,"wins":24,"losses":41}}]},"pregameCharts":{"homeTeam":{"teamId":1610612756,"teamCity":"Phoenix","teamName":"Suns","teamTricode":"PHX","statistics":{"points":115.7,"reboundsTotal":43.5,"assists":27,"steals":7.2,"blocks":5.3,"turnovers":12.6,"fieldGoalsPercentage":0.471,"threePointersPercentage":0.379,"freeThrowsPercentage":0.799,"pointsInThePaint":47.4,"pointsSecondChance":15.4,"pointsFastBreak":11.1,"playerPtsLeaderFirstName":"Devin","playerPtsLeaderFamilyName":"Booker","playerPtsLeaderId":1626164,"playerPtsLeaderPts":28,"playerRebLeaderFirstName":"Deandre","playerRebLeaderFamilyName":"Ayton","playerRebLeaderId":1629028,"playerRebLeaderReb":9.7,"playerAstLeaderFirstName":"Devin","playerAstLeaderFamilyName":"Booker","playerAstLeaderId":1626164,"playerAstLeaderAst":5.8,"playerBlkLeaderFirstName":"Bismack","playerBlkLeaderFamilyName":"Biyombo","playerBlkLeaderId":202687,"playerBlkLeaderBlk":1.38}},"awayTeam":{"teamId":1610612764,"teamCity":"Washington","teamName":"Wizards","teamTricode":"WAS","statistics":{"points":110.7,"reboundsTotal":43.7,"assists":24.8,"steals":6.9,"blocks":5.6,"turnovers":13.1,"fieldGoalsPercentage":0.473,"threePointersPercentage":0.347,"freeThrowsPercentage":0.76,"pointsInThePaint":50.4,"pointsSecondChance":12.8,"pointsFastBreak":11.8,"playerPtsLeaderFirstName":"Kristaps","playerPtsLeaderFamilyName":"Porzingis","playerPtsLeaderId":204001,"playerPtsLeaderPts":22.4,"playerRebLeaderFirstName":"Kristaps","playerRebLeaderFamilyName":"Porzingis","playerRebLeaderId":204001,"playerRebLeaderReb":8.9,"playerAstLeaderFirstName":"Monte","playerAstLeaderFamilyName":"Morris","playerAstLeaderId":1628420,"playerAstLeaderAst":5.1,"playerBlkLeaderFirstName":"Kristaps","playerBlkLeaderFamilyName":"Porzingis","playerBlkLeaderId":204001,"playerBlkLeaderBlk":1.48}}},"postgameCharts":{"homeTeam":{"teamId":1610612756,"teamCity":"Phoenix","teamName":"Suns","teamTricode":"PHX","statistics":{"points":110,"reboundsTotal":44,"assists":26,"steals":2,"blocks":1,"turnovers":14,"fieldGoalsPercentage":0.461,"threePointersPercentage":0.406,"freeThrowsPercentage":0.789,"pointsInThePaint":48,"pointsSecondChance":18,"pointsFastBreak":5,"biggestLead":10,"leadChanges":11,"timesTied":8,"biggestScoringRun":15,"turnoversTeam":0,"turnoversTotal":14,"reboundsTeam":9,"pointsFromTurnovers":25,"benchPoints":50,"playerPtsLeaderFirstName":"Landry","playerPtsLeaderFamilyName":"Shamet","playerPtsLeaderId":1629013,"playerPtsLeaderPts":31,"playerRebLeaderFirstName":"Deandre","playerRebLeaderFamilyName":"Ayton","playerRebLeaderId":1629028,"playerRebLeaderReb":13,"playerAstLeaderFirstName":"Chris","playerAstLeaderFamilyName":"Paul","playerAstLeaderId":101108,"playerAstLeaderAst":11,"playerBlkLeaderFirstName":"Deandre","playerBlkLeaderFamilyName":"Ayton","playerBlkLeaderId":1629028,"playerBlkLeaderBlk":1}},"awayTeam":{"teamId":1610612764,"teamCity":"Washington","teamName":"Wizards","teamTricode":"WAS","statistics":{"points":113,"reboundsTotal":41,"assists":22,"steals":9,"blocks":4,"turnovers":9,"fieldGoalsPercentage":0.475,"threePointersPercentage":0.407,"freeThrowsPercentage":0.703,"pointsInThePaint":48,"pointsSecondChance":14,"pointsFastBreak":16,"biggestLead":17,"leadChanges":11,"timesTied":8,"biggestScoringRun":15,"turnoversTeam":1,"turnoversTotal":10,"reboundsTeam":11,"pointsFromTurnovers":8,"benchPoints":20,"playerPtsLeaderFirstName":"Kyle","playerPtsLeaderFamilyName":"Kuzma","playerPtsLeaderId":1628398,"playerPtsLeaderPts":29,"playerRebLeaderFirstName":"Deni","playerRebLeaderFamilyName":"Avdija","playerRebLeaderId":1630166,"playerRebLeaderReb":10,"playerAstLeaderFirstName":"Kyle","playerAstLeaderFamilyName":"Kuzma","playerAstLeaderId":1628398,"playerAstLeaderAst":6,"playerBlkLeaderFirstName":"Taj","playerBlkLeaderFamilyName":"Gibson","playerBlkLeaderId":201959,"playerBlkLeaderBlk":1}}},"videoAvailableFlag":1,"ptAvailable":0,"ptXYZAvailable":0,"whStatus":1,"hustleStatus":1,"historicalStatus":0,"gameSubtype":"","branchUrl":"https://nba.app.link/?$deeplink_path=gametime%3A%2F%2Fgame%2F0022200464","homeTeamPlayers":[{"personId":202687,"name":"Bismack Biyombo","nameI":"B. Biyombo","firstName":"Bismack","familyName":"Biyombo","jerseyNum":"18"},{"personId":1629013,"name":"Landry Shamet","nameI":"L. Shamet","firstName":"Landry","familyName":"Shamet","jerseyNum":"14"},{"personId":1627814,"name":"Damion Lee","nameI":"D. Lee","firstName":"Damion","familyName":"Lee","jerseyNum":"10"},{"personId":101108,"name":"Chris Paul","nameI":"C. Paul","firstName":"Chris","familyName":"Paul","jerseyNum":"3"},{"personId":1630688,"name":"Ish Wainright","nameI":"I. Wainright","firstName":"Ish","familyName":"Wainright","jerseyNum":"12"},{"personId":203967,"name":"Dario Saric","nameI":"D. Saric","firstName":"Dario","familyName":"Saric","jerseyNum":"20"},{"personId":1629028,"name":"Deandre Ayton","nameI":"D. Ayton","firstName":"Deandre","familyName":"Ayton","jerseyNum":"22"},{"personId":1628969,"name":"Mikal Bridges","nameI":"M. Bridges","firstName":"Mikal","familyName":"Bridges","jerseyNum":"25"},{"personId":1630613,"name":"Duane Washington Jr.","nameI":"D. Washington Jr.","firstName":"Duane","familyName":"Washington Jr.","jerseyNum":"4"},{"personId":1628470,"name":"Torrey Craig","nameI":"T. Craig","firstName":"Torrey","familyName":"Craig","jerseyNum":"0"},{"personId":1626164,"name":"Devin Booker","nameI":"D. Booker","firstName":"Devin","familyName":"Booker","jerseyNum":"1"}],"awayTeamPlayers":[{"personId":1630557,"name":"Corey Kispert","nameI":"C. Kispert","firstName":"Corey","familyName":"Kispert","jerseyNum":"24"},{"personId":203078,"name":"Bradley Beal","nameI":"B. Beal","firstName":"Bradley","familyName":"Beal","jerseyNum":"3"},{"personId":1628398,"name":"Kyle Kuzma","nameI":"K. Kuzma","firstName":"Kyle","familyName":"Kuzma","jerseyNum":"33"},{"personId":1630166,"name":"Deni Avdija","nameI":"D. Avdija","firstName":"Deni","familyName":"Avdija","jerseyNum":"9"},{"personId":1630692,"name":"Jordan Goodwin","nameI":"J. Goodwin","firstName":"Jordan","familyName":"Goodwin","jerseyNum":"7"},{"personId":1630264,"name":"Anthony Gill","nameI":"A. Gill","firstName":"Anthony","familyName":"Gill","jerseyNum":"16"},{"personId":201959,"name":"Taj Gibson","nameI":"T. Gibson","firstName":"Taj","familyName":"Gibson","jerseyNum":"67"},{"personId":1628420,"name":"Monte Morris","nameI":"M. Morris","firstName":"Monte","familyName":"Morris","jerseyNum":"22"},{"personId":1629655,"name":"Daniel Gafford","nameI":"D. Gafford","firstName":"Daniel","familyName":"Gafford","jerseyNum":"21"},{"personId":203115,"name":"Will Barton","nameI":"W. Barton","firstName":"Will","familyName":"Barton","jerseyNum":"5"},{"personId":204001,"name":"Kristaps Porzingis","nameI":"K. Porzingis","firstName":"Kristaps","familyName":"Porzingis","jerseyNum":"6"}],"pbOdds":{}}